column_toggle/__init__.py
column_toggle/admin.py
column_toggle/static/column_toggle/column_toggle.css
column_toggle/static/column_toggle/column_toggle.js
column_toggle/templates/column_toggle/change_list.html
column_toggle/templates/column_toggle/column_toggle.html
django_admin_column_toggle-0.4.2.dist-info/LICENCE
django_admin_column_toggle-0.4.2.dist-info/METADATA
django_admin_column_toggle-0.4.2.dist-info/WHEEL
django_admin_column_toggle-0.4.2.dist-info/RECORD
