Metadata-Version: 2.1
Name: django-admin-column-toggle
Version: 0.4.2
Summary: A reusable Django package to add column toggle functionality in the Django admin interface.
Home-page: https://github.com/engwerda/Django-Admin-Column-Toggle
License: MIT
Keywords: django
Author: Simon Engwerda
Author-email: simon@engwerda.net
Requires-Python: >=3.8,<4.0
Classifier: License :: OSI Approved :: MIT License
Classifier: Programming Language :: Python :: 3
Classifier: Programming Language :: Python :: 3.8
Classifier: Programming Language :: Python :: 3.9
Classifier: Programming Language :: Python :: 3.10
Classifier: Programming Language :: Python :: 3.11
Classifier: Programming Language :: Python :: 3.12
Requires-Dist: django (>=4.2)
Project-URL: Repository, https://github.com/engwerda/Django-Admin-Column-Toggle
